autospeX/__init__.py
autospeX/model.py
autospeX-0.0.1.dist-info/METADATA
autospeX-0.0.1.dist-info/WHEEL
autospeX-0.0.1.dist-info/top_level.txt
autospeX-0.0.1.dist-info/zip-safe
autospeX-0.0.1.dist-info/RECORD
